Metadata-Version: 2.1
Name: pysystemd
Version: 1.1
Summary: A systemd binding Library in Python
Home-page: https://codeberg.org/alimiracle/pysystemd
Author: alimiracle
Author-email: alimiracle@riseup.net
License: LGPL v3
Keywords: services,init,systemd
Platform: UNKNOWN
Classifier: Programming Language :: Python :: 3
Classifier: License :: OSI Approved :: GNU Lesser General Public License v3 (LGPLv3)
Classifier: Operating System :: POSIX :: Linux
Classifier: Topic :: Software Development :: Libraries :: Python Modules
License-File: LICENSE
